src/__init__.py
src/_client.py
src/client.py
src/func.py
src/manager.py
src/protocol.py
src/regdecorator.py
src/server.py
src/utils.py
outlinr-0.0.1.dist-info/LICENSE
outlinr-0.0.1.dist-info/METADATA
outlinr-0.0.1.dist-info/WHEEL
outlinr-0.0.1.dist-info/top_level.txt
outlinr-0.0.1.dist-info/RECORD
