Metadata-Version: 2.1
Name: outlinr
Version: 0.0.1
Summary: Outlier
Home-page: UNKNOWN
Author: Thetis
Author-email: 736396627@qq.com
License: UNKNOWN
Platform: UNKNOWN
Requires-Python: >3.6
